setup.cfg
setup.py
rada_zrada/__init__.py
rada_zrada/descriptors.py
rada_zrada/models.py
rada_zrada/start.py
rada_zrada/utils.py
rada_zrada.egg-info/PKG-INFO
rada_zrada.egg-info/SOURCES.txt
rada_zrada.egg-info/dependency_links.txt
rada_zrada.egg-info/entry_points.txt
rada_zrada.egg-info/not-zip-safe
rada_zrada.egg-info/requires.txt
rada_zrada.egg-info/top_level.txt