Metadata-Version: 1.0
Name: rada-zrada
Version: 0.1.dev0
Summary: Rada Zrada
Home-page: UNKNOWN
Author: Unknown
Author-email: UNKNOWN
License: UNKNOWN
Platform: UNKNOWN
